sqjobs/__init__.py
sqjobs/cli.py
sqjobs/exceptions.py
sqjobs/job.py
sqjobs/metadata.py
sqjobs/utils.py
sqjobs/worker.py
sqjobs/brokers/__init__.py
sqjobs/brokers/base.py
sqjobs/brokers/eager.py
sqjobs/brokers/multiqueue.py
sqjobs/brokers/standard.py
sqjobs/connectors/__init__.py
sqjobs/connectors/base.py
sqjobs/connectors/dummy.py
sqjobs/connectors/sqs.py
sqjobs/contrib/__init__.py
sqjobs/contrib/sentry.py
sqjobs/contrib/django/__init__.py
sqjobs/contrib/django/djsqjobs/__init__.py
sqjobs/contrib/django/djsqjobs/finders.py
sqjobs/contrib/django/djsqjobs/models.py
sqjobs/contrib/django/djsqjobs/result_job.py
sqjobs/contrib/django/djsqjobs/utils.py
sqjobs/contrib/django/djsqjobs/management/__init__.py
sqjobs/contrib/django/djsqjobs/management/commands/__init__.py
sqjobs/contrib/django/djsqjobs/management/commands/sqjobs.py
sqjobs/tests/__init__.py
sqjobs/tests/broker_test.py
sqjobs/tests/connector_test.py
sqjobs/tests/fixtures.py
sqjobs/tests/job_test.py
sqjobs/tests/utils_test.py
sqjobs/tests/worker_test.py
sqjobs/tests/contrib/__init__.py
sqjobs/tests/contrib/django/__init__.py
sqjobs/tests/contrib/django/django_contrib.py
sqjobs/tests/contrib/django/django_fixtures.py
sqjobs/tests/contrib/django/tests.py
sqjobs_tf-0.8.10.dist-info/LICENSE
sqjobs_tf-0.8.10.dist-info/METADATA
sqjobs_tf-0.8.10.dist-info/WHEEL
sqjobs_tf-0.8.10.dist-info/entry_points.txt
sqjobs_tf-0.8.10.dist-info/top_level.txt
sqjobs_tf-0.8.10.dist-info/RECORD
